osa/__init__.py
osa/app.py
osa/cli.py
osa/constants.py
osa/ctx.py
osa/error_handlers.py
osa/exceptions.py
osa/globals.py
osa/local_proxy.py
osa/request_handler.py
osa/router.py
osa/static_file_handler.py
osa/template_engine.py
tests/__init__.py
tests/conftest.py
tests/test_api.py
tests/test_app.py
tests/test_cli.py
tests/test_context.py
tests/test_errorhandler.py
tests/test_exception.py
tests/test_route.py
tests/test_router.py
tests/test_template_engine.py
tests/utils.py
osa_web_framework-0.0.3.dist-info/METADATA
osa_web_framework-0.0.3.dist-info/WHEEL
osa_web_framework-0.0.3.dist-info/entry_points.txt
osa_web_framework-0.0.3.dist-info/top_level.txt
osa_web_framework-0.0.3.dist-info/RECORD
