Metadata-Version: 2.1
Name: osa-web-framework
Version: 0.0.3
Summary: A simple web framework for Python developers to learn how some fundamental concepts of web frameworks work under the hood.
Author: Alyahyawy Osama
Author-email: alyhyawyosama@gmail.com
Classifier: Programming Language :: Python :: 3
Classifier: License :: OSI Approved :: MIT License
Classifier: Operating System :: OS Independent
Requires-Python: >=3.6
Requires-Dist: click
Requires-Dist: webob
Requires-Dist: requests
Requires-Dist: parse
Requires-Dist: requests-wsgi-adapter
Requires-Dist: whitenoise
Requires-Dist: jinja2
